haystack_integrations/components/retrievers/py.typed
haystack_integrations/components/retrievers/astra/__init__.py
haystack_integrations/components/retrievers/astra/retriever.py
haystack_integrations/document_stores/py.typed
haystack_integrations/document_stores/astra/__init__.py
haystack_integrations/document_stores/astra/astra_client.py
haystack_integrations/document_stores/astra/document_store.py
haystack_integrations/document_stores/astra/errors.py
haystack_integrations/document_stores/astra/filters.py
astra_haystack-3.1.0.dist-info/METADATA
astra_haystack-3.1.0.dist-info/WHEEL
astra_haystack-3.1.0.dist-info/licenses/LICENSE
astra_haystack-3.1.0.dist-info/RECORD
