Metadata-Version: 2.4
Name: astra-haystack
Version: 3.1.0
Project-URL: Documentation, https://github.com/deepset-ai/haystack-core-integrations/tree/main/integrations/astra#readme
Project-URL: Issues, https://github.com/deepset-ai/haystack-core-integrations/issues
Project-URL: Source, https://github.com/deepset-ai/haystack-core-integrations/tree/main/integrations/astra
Author-email: Anant Corporation <support@anant.us>
License-Expression: Apache-2.0
License-File: LICENSE
Classifier: Development Status :: 4 - Beta
Classifier: License :: OSI Approved :: Apache Software License
Classifier: Programming Language :: Python
Classifier: Programming Language :: Python :: 3.9
Classifier: Programming Language :: Python :: 3.10
Classifier: Programming Language :: Python :: 3.11
Classifier: Programming Language :: Python :: 3.12
Classifier: Programming Language :: Python :: 3.13
Classifier: Programming Language :: Python :: Implementation :: CPython
Classifier: Programming Language :: Python :: Implementation :: PyPy
Requires-Python: >=3.9
Requires-Dist: astrapy<2.0,>=1.5.0
Requires-Dist: haystack-ai>=2.11.0
Requires-Dist: pydantic
Requires-Dist: typing-extensions
